olive/__init__.py
olive/metadata.py
oliv_testing-0.0.1.dist-info/METADATA
oliv_testing-0.0.1.dist-info/WHEEL
oliv_testing-0.0.1.dist-info/top_level.txt
oliv_testing-0.0.1.dist-info/RECORD
