Metadata-Version: 2.1
Name: oliv-testing
Version: 0.0.1
Summary: a python wrapper for an AIS Database API
Home-page: https://github.com/GeoBigData/AISDatabase
Author: Elizabeth Golden, Rachel Wegener, Melissa Dozier
Author-email: elizabeth.golden@digitalglobe.com
License: UNKNOWN
Platform: UNKNOWN
Requires-Python: >=3
Requires-Dist: requests
Requires-Dist: python-dotenv
